Workbook

Sheet Sheet4
B3: Values
A4: Row Labels | B4: Average of Salary | C4: Sum of Training_Cost | D4: Count of Employee_ID | E4: Sum of Annual_Cost | F4: % of Total Cost
A5: Engineering | B5: 883133.33 | C5: 3627000 | D5: 150 | E5: 151838000 | F5: 0.33896421
A6: Finance | B6: 742906.67 | C6: 1790000 | D6: 75 | E6: 64233000 | F6: 0.1433942
A7: Human Resources | B7: 668960 | C7: 1176000 | D7: 50 | E7: 38638000 | F7: 0.08625574
A8: Operations | B8: 727976 | C8: 3067000 | D8: 125 | E8: 104851000 | F8: 0.2340701
A9: Sales | B9: 766490 | C9: 2432000 | D9: 100 | E9: 88387000 | F9: 0.19731575
A10: Grand Total | B10: 778564 | C10: 12092000 | D10: 500 | E10: 447947000 | F10: 1

Sheet Employee_Data
A1: Employee_ID | B1: Department | C1: Role | D1: Job_Level | E1: Salary | F1: Benefits | G1: Training_Cost | H1: Status | I1: Total_Compensation | J1: Annual_Cost
A2: EMP0001 | B2: Engineering | C2: Data Engineer | D2: =IF(OR(ISNUMBER(SEARCH("Manager",C2)),ISNUMBER(SEARCH("Controller",C2))),"Leadership",IF(OR(ISNUMBER(SEARCH("Senior",C2)),ISNUMBER(SEARCH("Regional",C2))),"Senior",IF(OR(ISNUMBER(SEARCH("Engineer",C2)),ISNUMBER(SEARCH("Analyst",C2)),ISNUMBER(SEARCH("Specialist",C2)),ISNUMBER(SEARCH("Business Partner",C2)),ISNUMBER(SEARCH("Account Manager",C2))),"Mid","Entry"))) -> Mid | E2: 815000 | F2: 90000 | G2: 22000 | H2: Active | I2: =E2+F2 -> 905000 | J2: =I2+G2 -> 927000
A3: EMP0002 | B3: Engineering | C3: Software Engineer | D3: =IF(OR(ISNUMBER(SEARCH("Manager",C3)),ISNUMBER(SEARCH("Controller",C3))),"Leadership",IF(OR(ISNUMBER(SEARCH("Senior",C3)),ISNUMBER(SEARCH("Regional",C3))),"Senior",IF(OR(ISNUMBER(SEARCH("Engineer",C3)),ISNUMBER(SEARCH("Analyst",C3)),ISNUMBER(SEARCH("Specialist",C3)),ISNUMBER(SEARCH("Business Partner",C3)),ISNUMBER(SEARCH("Account Manager",C3))),"Mid","Entry"))) -> Mid | E3: 765000 | F3: 93000 | G3: 30000 | H3: Exit | I3: =E3+F3 -> 858000 | J3: =I3+G3 -> 888000
A4: EMP0003 | B4: Engineering | C4: Software Engineer | D4: =IF(OR(ISNUMBER(SEARCH("Manager",C4)),ISNUMBER(SEARCH("Controller",C4))),"Leadership",IF(OR(ISNUMBER(SEARCH("Senior",C4)),ISNUMBER(SEARCH("Regional",C4))),"Senior",IF(OR(ISNUMBER(SEARCH("Engineer",C4)),ISNUMBER(SEARCH("Analyst",C4)),ISNUMBER(SEARCH("Specialist",C4)),ISNUMBER(SEARCH("Business Partner",C4)),ISNUMBER(SEARCH("Account Manager",C4))),"Mid","Entry"))) -> Mid | E4: 685000 | F4: 85000 | G4: 22000 | H4: Active | I4: =E4+F4 -> 770000 | J4: =I4+G4 -> 792000
A5: EMP0004 | B5: Engineering | C5: Data Engineer | D5: =IF(OR(ISNUMBER(SEARCH("Manager",C5)),ISNUMBER(SEARCH("Controller",C5))),"Leadership",IF(OR(ISNUMBER(SEARCH("Senior",C5)),ISNUMBER(SEARCH("Regional",C5))),"Senior",IF(OR(ISNUMBER(SEARCH("Engineer",C5)),ISNUMBER(SEARCH("Analyst",C5)),ISNUMBER(SEARCH("Specialist",C5)),ISNUMBER(SEARCH("Business Partner",C5)),ISNUMBER(SEARCH("Account Manager",C5))),"Mid","Entry"))) -> Mid | E5: 893000 | F5: 105000 | G5: 25000 | H5: Active | I5: =E5+F5 -> 998000 | J5: =I5+G5 -> 1023000
A6: EMP0005 | B6: Engineering | C6: Software Engineer | D6: =IF(OR(ISNUMBER(SEARCH("Manager",C6)),ISNUMBER(SEARCH("Controller",C6))),"Leadership",IF(OR(ISNUMBER(SEARCH("Senior",C6)),ISNUMBER(SEARCH("Regional",C6))),"Senior",IF(OR(ISNUMBER(SEARCH("Engineer",C6)),ISNUMBER(SEARCH("Analyst",C6)),ISNUMBER(SEARCH("Specialist",C6)),ISNUMBER(SEARCH("Business Partner",C6)),ISNUMBER(SEARCH("Account Manager",C6))),"Mid","Entry"))) -> Mid | E6: 776000 | F6: 99000 | G6: 28000 | H6: Active | I6: =E6+F6 -> 875000 | J6: =I6+G6 -> 903000
A7: EMP0006 | B7: Engineering | C7: Software Engineer | D7: =IF(OR(ISNUMBER(SEARCH("Manager",C7)),ISNUMBER(SEARCH("Controller",C7))),"Leadership",IF(OR(ISNUMBER(SEARCH("Senior",C7)),ISNUMBER(SEARCH("Regional",C7))),"Senior",IF(OR(ISNUMBER(SEARCH("Engineer",C7)),ISNUMBER(SEARCH("Analyst",C7)),ISNUMBER(SEARCH("Specialist",C7)),ISNUMBER(SEARCH("Business Partner",C7)),ISNUMBER(SEARCH("Account Manager",C7))),"Mid","Entry"))) -> Mid | E7: 769000 | F7: 80000 | G7: 30000 | H7: Active | I7: =E7+F7 -> 849000 | J7: =I7+G7 -> 879000
A8: EMP0007 | B8: Engineering | C8: DevOps Engineer | D8: =IF(OR(ISNUMBER(SEARCH("Manager",C8)),ISNUMBER(SEARCH("Controller",C8))),"Leadership",IF(OR(ISNUMBER(SEARCH("Senior",C8)),ISNUMBER(SEARCH("Regional",C8))),"Senior",IF(OR(ISNUMBER(SEARCH("Engineer",C8)),ISNUMBER(SEARCH("Analyst",C8)),ISNUMBER(SEARCH("Specialist",C8)),ISNUMBER(SEARCH("Business Partner",C8)),ISNUMBER(SEARCH("Account Manager",C8))),"Mid","Entry"))) -> Mid | E8: 878000 | F8: 116000 | G8: 35000 | H8: Active | I8: =E8+F8 -> 994000 | J8: =I8+G8 -> 1029000
A9: EMP0008 | B9: Engineering | C9: Engineering Manager | D9: =IF(OR(ISNUMBER(SEARCH("Manager",C9)),ISNUMBER(SEARCH("Controller",C9))),"Leadership",IF(OR(ISNUMBER(SEARCH("Senior",C9)),ISNUMBER(SEARCH("Regional",C9))),"Senior",IF(OR(ISNUMBER(SEARCH("Engineer",C9)),ISNUMBER(SEARCH("Analyst",C9)),ISNUMBER(SEARCH("Specialist",C9)),ISNUMBER(SEARCH("Business Partner",C9)),ISNUMBER(SEARCH("Account Manager",C9))),"Mid","Entry"))) -> Leadership | E9: 1426000 | F9: 174000 | G9: 28000 | H9: Active | I9: =E9+F9 -> 1600000 | J9: =I9+G9 -> 1628000
A10: EMP0009 | B10: Engineering | C10: Data Engineer | D10: =IF(OR(ISNUMBER(SEARCH("Manager",C10)),ISNUMBER(SEARCH("Controller",C10))),"Leadership",IF(OR(ISNUMBER(SEARCH("Senior",C10)),ISNUMBER(SEARCH("Regional",C10))),"Senior",IF(OR(ISNUMBER(SEARCH("Engineer",C10)),ISNUMBER(SEARCH("Analyst",C10)),ISNUMBER(SEARCH("Specialist",C10)),ISNUMBER(SEARCH("Business Partner",C10)),ISNUMBER(SEARCH("Account Manager",C10))),"Mid","Entry"))) -> Mid | E10: 819000 | F10: 89000 | G10: 25000 | H10: Active | I10: =E10+F10 -> 908000 | J10: =I10+G10 -> 933000
A11: EMP0010 | B11: Engineering | C11: QA Engineer | D11: =IF(OR(ISNUMBER(SEARCH("Manager",C11)),ISNUMBER(SEARCH("Controller",C11))),"Leadership",IF(OR(ISNUMBER(SEARCH("Senior",C11)),ISNUMBER(SEARCH("Regional",C11))),"Senior",IF(OR(ISNUMBER(SEARCH("Engineer",C11)),ISNUMBER(SEARCH("Analyst",C11)),ISNUMBER(SEARCH("Specialist",C11)),ISNUMBER(SEARCH("Business Partner",C11)),ISNUMBER(SEARCH("Account Manager",C11))),"Mid","Entry"))) -> Mid | E11: 709000 | F11: 82000 | G11: 35000 | H11: Active | I11: =E11+F11 -> 791000 | J11: =I11+G11 -> 826000
A12: EMP0011 | B12: Engineering | C12: Senior Software Engineer | D12: =IF(OR(ISNUMBER(SEARCH("Manager",C12)),ISNUMBER(SEARCH("Controller",C12))),"Leadership",IF(OR(ISNUMBER(SEARCH("Senior",C12)),ISNUMBER(SEARCH("Regional",C12))),"Senior",IF(OR(ISNUMBER(SEARCH("Engineer",C12)),ISNUMBER(SEARCH("Analyst",C12)),ISNUMBER(SEARCH("Specialist",C12)),ISNUMBER(SEARCH("Business Partner",C12)),ISNUMBER(SEARCH("Account Manager",C12))),"Mid","Entry"))) -> Senior | E12: 1080000 | F12: 117000 | G12: 25000 | H12: Active | I12: =E12+F12 -> 1197000 | J12: =I12+G12 -> 1222000
A13: EMP0012 | B13: Engineering | C13: Data Engineer | D13: =IF(OR(ISNUMBER(SEARCH("Manager",C13)),ISNUMBER(SEARCH("Controller",C13))),"Leadership",IF(OR(ISNUMBER(SEARCH("Senior",C13)),ISNUMBER(SEARCH("Regional",C13))),"Senior",IF(OR(ISNUMBER(SEARCH("Engineer",C13)),ISNUMBER(SEARCH("Analyst",C13)),ISNUMBER(SEARCH("Specialist",C13)),ISNUMBER(SEARCH("Business Partner",C13)),ISNUMBER(SEARCH("Account Manager",C13))),"Mid","Entry"))) -> Mid | E13: 824000 | F13: 103000 | G13: 22000 | H13: Active | I13: =E13+F13 -> 927000 | J13: =I13+G13 -> 949000
... A501: EMP0500 | B501: Operations | C501: Senior Operations Executive | D501: =IF(OR(ISNUMBER(SEARCH("Manager",C501)),ISNUMBER(SEARCH("Controller",C501))),"Leadership",IF(OR(ISNUMBER(SEARCH("Senior",C501)),ISNUMBER(SEARCH("Regional",C501))),"Senior",IF(OR(ISNUMBER(SEARCH("Engineer",C501)),ISNUMBER(SEARCH("Analyst",C501)),ISNUMBER(SEARCH("Specialist",C501)),ISNUMBER(SEARCH("Business Partner",C501)),ISNUMBER(SEARCH("Account Manager",C501))),"Mid","Entry"))) -> Senior | E501: 837000 | F501: 96000 | G501: 18000 | H501: Active | I501: =E501+F501 -> 933000 | J501: =I501+G501 -> 951000

Sheet Workforce_Plan
A1: Department | B1: Current_Headcount | C1: Planned_Hires | D1: Planned_Exits | E1: Forecasted_Headcount | F1: Avg_Salary | G1: Budget_Allocation
A2: Engineering | B2: 150 | C2: 28 | D2: 12 | E2: =B2+C2-D2 -> 166 | F2: 883000 | G2: 175000000
A3: Sales | B3: 100 | C3: 18 | D3: 8 | E3: =B3+C3-D3 -> 110 | F3: 766000 | G3: 82000000
A4: Finance | B4: 75 | C4: 10 | D4: 5 | E4: =B4+C4-D4 -> 80 | F4: 743000 | G4: 50000000
A5: Human Resources | B5: 50 | C5: 7 | D5: 3 | E5: =B5+C5-D5 -> 54 | F5: 669000 | G5: 30000000
A6: Operations | B6: 125 | C6: 22 | D6: 10 | E6: =B6+C6-D6 -> 137 | F6: 728000 | G6: 100000000

Sheet Workforce_KPIs
A1: KPI | B1: Value
A2: Current Headcount | B2: =SUM(Workforce_Plan!B2:B6) -> 500
A3: Planned Hires | B3: =SUM(Workforce_Plan!C2:C6) -> 85
A4: Planned Exits | B4: =SUM(Workforce_Plan!D2:D6) -> 38
A5: Headcount Forecast | B5: =B2+B3-B4 -> 547
A6: Total HR Spend | B6: =SUM(Employee_Data!J2:J501) -> 447947000
A7: Cost per Employee | B7: =B6/B2 -> 895894
A8: Training Cost | B8: =SUM(Employee_Data!G2:G501) -> 12092000
A9: Training Spend per Employee | B9: =B8/B2 -> 24184
A10: Budget Allocation | B10: =SUM(Workforce_Plan!G2:G6) -> 437000000
A11: Budget Utilization % | B11: =B6/B10 -> 1.0250503

Sheet Sheet3
B3: Values
A4: Row Labels | B4: Sum of Planned_Salary | C4: Sum of Actual_Salary | D4: Sum of Salary_Variance | E4: Sum of Planned_Training | F4: Sum of Actual Training | G4: Sum of Training Var. | H4: Sum of Total Planned | I4: Sum of Total Actual | J4: Sum of Total Var.
A5: Engineering | B5: 139101000 | C5: 132470000 | D5: -6631000 | E5: 3461000 | F5: 3627000 | G5: 166000 | H5: 142562000 | I5: 136097000 | J5: -6465000
A6: Finance | B6: 58501000 | C6: 55718000 | D6: -2783000 | E6: 1707000 | F6: 1790000 | G6: 83000 | H6: 60208000 | I6: 57508000 | J6: -2700000
A7: Human Resources | B7: 35120000 | C7: 33448000 | D7: -1672000 | E7: 1121000 | F7: 1176000 | G7: 55000 | H7: 36241000 | I7: 34624000 | J7: -1617000
A8: Operations | B8: 95558000 | C8: 90997000 | D8: -4561000 | E8: 2925000 | F8: 3067000 | G8: 142000 | H8: 98483000 | I8: 94064000 | J8: -4419000
A9: Sales | B9: 80485000 | C9: 76649000 | D9: -3836000 | E9: 2319000 | F9: 2432000 | G9: 113000 | H9: 82804000 | I9: 79081000 | J9: -3723000
A10: Grand Total | B10: 408765000 | C10: 389282000 | D10: -19483000 | E10: 11533000 | F10: 12092000 | G10: 559000 | H10: 420298000 | I10: 401374000 | J10: -18924000

Sheet Budget_vs_Actual
A1: Employee_ID | B1: Department | C1: Planned_Salary | D1: Actual_Salary | E1: Salary_Variance | F1: Planned_Training | G1: Actual Training | H1: Training Var. | I1: Total Planned | J1: Total Actual | K1: Total Var.
A2: =Employee_Data!A2 -> EMP0001 | B2: =Employee_Data!B2 -> Engineering | C2: =ROUND(Employee_Data!E2*1.05,-3) -> 856000 | D2: =Employee_Data!E2 -> 815000 | E2: =D2-C2 -> -41000 | F2: =ROUND(Employee_Data!G2*0.95,-3) -> 21000 | G2: =Employee_Data!G2 -> 22000 | H2: =G2-F2 -> 1000 | I2: =C2+F2 -> 877000 | J2: =D2+G2 -> 837000 | K2: =J2-I2 -> -40000
A3: =Employee_Data!A3 -> EMP0002 | B3: =Employee_Data!B3 -> Engineering | C3: =ROUND(Employee_Data!E3*1.05,-3) -> 803000 | D3: =Employee_Data!E3 -> 765000 | E3: =D3-C3 -> -38000 | F3: =ROUND(Employee_Data!G3*0.95,-3) -> 29000 | G3: =Employee_Data!G3 -> 30000 | H3: =G3-F3 -> 1000 | I3: =C3+F3 -> 832000 | J3: =D3+G3 -> 795000 | K3: =J3-I3 -> -37000
A4: =Employee_Data!A4 -> EMP0003 | B4: =Employee_Data!B4 -> Engineering | C4: =ROUND(Employee_Data!E4*1.05,-3) -> 719000 | D4: =Employee_Data!E4 -> 685000 | E4: =D4-C4 -> -34000 | F4: =ROUND(Employee_Data!G4*0.95,-3) -> 21000 | G4: =Employee_Data!G4 -> 22000 | H4: =G4-F4 -> 1000 | I4: =C4+F4 -> 740000 | J4: =D4+G4 -> 707000 | K4: =J4-I4 -> -33000
A5: =Employee_Data!A5 -> EMP0004 | B5: =Employee_Data!B5 -> Engineering | C5: =ROUND(Employee_Data!E5*1.05,-3) -> 938000 | D5: =Employee_Data!E5 -> 893000 | E5: =D5-C5 -> -45000 | F5: =ROUND(Employee_Data!G5*0.95,-3) -> 24000 | G5: =Employee_Data!G5 -> 25000 | H5: =G5-F5 -> 1000 | I5: =C5+F5 -> 962000 | J5: =D5+G5 -> 918000 | K5: =J5-I5 -> -44000
A6: =Employee_Data!A6 -> EMP0005 | B6: =Employee_Data!B6 -> Engineering | C6: =ROUND(Employee_Data!E6*1.05,-3) -> 815000 | D6: =Employee_Data!E6 -> 776000 | E6: =D6-C6 -> -39000 | F6: =ROUND(Employee_Data!G6*0.95,-3) -> 27000 | G6: =Employee_Data!G6 -> 28000 | H6: =G6-F6 -> 1000 | I6: =C6+F6 -> 842000 | J6: =D6+G6 -> 804000 | K6: =J6-I6 -> -38000
A7: =Employee_Data!A7 -> EMP0006 | B7: =Employee_Data!B7 -> Engineering | C7: =ROUND(Employee_Data!E7*1.05,-3) -> 807000 | D7: =Employee_Data!E7 -> 769000 | E7: =D7-C7 -> -38000 | F7: =ROUND(Employee_Data!G7*0.95,-3) -> 29000 | G7: =Employee_Data!G7 -> 30000 | H7: =G7-F7 -> 1000 | I7: =C7+F7 -> 836000 | J7: =D7+G7 -> 799000 | K7: =J7-I7 -> -37000
A8: =Employee_Data!A8 -> EMP0007 | B8: =Employee_Data!B8 -> Engineering | C8: =ROUND(Employee_Data!E8*1.05,-3) -> 922000 | D8: =Employee_Data!E8 -> 878000 | E8: =D8-C8 -> -44000 | F8: =ROUND(Employee_Data!G8*0.95,-3) -> 33000 | G8: =Employee_Data!G8 -> 35000 | H8: =G8-F8 -> 2000 | I8: =C8+F8 -> 955000 | J8: =D8+G8 -> 913000 | K8: =J8-I8 -> -42000
A9: =Employee_Data!A9 -> EMP0008 | B9: =Employee_Data!B9 -> Engineering | C9: =ROUND(Employee_Data!E9*1.05,-3) -> 1497000 | D9: =Employee_Data!E9 -> 1426000 | E9: =D9-C9 -> -71000 | F9: =ROUND(Employee_Data!G9*0.95,-3) -> 27000 | G9: =Employee_Data!G9 -> 28000 | H9: =G9-F9 -> 1000 | I9: =C9+F9 -> 1524000 | J9: =D9+G9 -> 1454000 | K9: =J9-I9 -> -70000
A10: =Employee_Data!A10 -> EMP0009 | B10: =Employee_Data!B10 -> Engineering | C10: =ROUND(Employee_Data!E10*1.05,-3) -> 860000 | D10: =Employee_Data!E10 -> 819000 | E10: =D10-C10 -> -41000 | F10: =ROUND(Employee_Data!G10*0.95,-3) -> 24000 | G10: =Employee_Data!G10 -> 25000 | H10: =G10-F10 -> 1000 | I10: =C10+F10 -> 884000 | J10: =D10+G10 -> 844000 | K10: =J10-I10 -> -40000
A11: =Employee_Data!A11 -> EMP0010 | B11: =Employee_Data!B11 -> Engineering | C11: =ROUND(Employee_Data!E11*1.05,-3) -> 744000 | D11: =Employee_Data!E11 -> 709000 | E11: =D11-C11 -> -35000 | F11: =ROUND(Employee_Data!G11*0.95,-3) -> 33000 | G11: =Employee_Data!G11 -> 35000 | H11: =G11-F11 -> 2000 | I11: =C11+F11 -> 777000 | J11: =D11+G11 -> 744000 | K11: =J11-I11 -> -33000
A12: =Employee_Data!A12 -> EMP0011 | B12: =Employee_Data!B12 -> Engineering | C12: =ROUND(Employee_Data!E12*1.05,-3) -> 1134000 | D12: =Employee_Data!E12 -> 1080000 | E12: =D12-C12 -> -54000 | F12: =ROUND(Employee_Data!G12*0.95,-3) -> 24000 | G12: =Employee_Data!G12 -> 25000 | H12: =G12-F12 -> 1000 | I12: =C12+F12 -> 1158000 | J12: =D12+G12 -> 1105000 | K12: =J12-I12 -> -53000
A13: =Employee_Data!A13 -> EMP0012 | B13: =Employee_Data!B13 -> Engineering | C13: =ROUND(Employee_Data!E13*1.05,-3) -> 865000 | D13: =Employee_Data!E13 -> 824000 | E13: =D13-C13 -> -41000 | F13: =ROUND(Employee_Data!G13*0.95,-3) -> 21000 | G13: =Employee_Data!G13 -> 22000 | H13: =G13-F13 -> 1000 | I13: =C13+F13 -> 886000 | J13: =D13+G13 -> 846000 | K13: =J13-I13 -> -40000
... A501: =Employee_Data!A501 -> EMP0500 | B501: =Employee_Data!B501 -> Operations | C501: =ROUND(Employee_Data!E501*1.05,-3) -> 879000 | D501: =Employee_Data!E501 -> 837000 | E501: =D501-C501 -> -42000 | F501: =ROUND(Employee_Data!G501*0.95,-3) -> 17000 | G501: =Employee_Data!G501 -> 18000 | H501: =G501-F501 -> 1000 | I501: =C501+F501 -> 896000 | J501: =D501+G501 -> 855000 | K501: =J501-I501 -> -41000
